netmiko_multihop/__init__.py
netmiko_multihop-0.2.1.dist-info/LICENSE
netmiko_multihop-0.2.1.dist-info/METADATA
netmiko_multihop-0.2.1.dist-info/WHEEL
netmiko_multihop-0.2.1.dist-info/top_level.txt
netmiko_multihop-0.2.1.dist-info/RECORD
