Metadata-Version: 2.1
Name: netmiko-multihop
Version: 0.2.1
Summary: Out of tree netmiko monkeypatch for multihop capability
Home-page: https://github.com/jinjamator/netmiko_multihop
Author: Wilhelm Putz
Author-email: wp@aci.guru
License: ASL V2
Classifier: License :: OSI Approved :: Apache Software License
Classifier: Programming Language :: Python :: 3.7
Classifier: Programming Language :: Python :: 3.8
Classifier: Topic :: System :: Installation/Setup
Classifier: Topic :: System :: Systems Administration
Classifier: Topic :: Utilities
Requires-Python: >=3.7
License-File: LICENSE
Requires-Dist: netmiko (>=4.1.2)
